appendfilename/__init__.py
appendfilename-2025.5.14.dist-info/METADATA
appendfilename-2025.5.14.dist-info/WHEEL
appendfilename-2025.5.14.dist-info/entry_points.txt
appendfilename-2025.5.14.dist-info/RECORD
