Metadata-Version: 2.1
Name: appendfilename
Version: 2025.5.14
Summary: Intelligent appending text to file names, considering file extensions and file tags
License: GPL-3.0-or-later
Keywords: file managing,file management,files,name,time,time-stamps
Author: Karl Voit
Author-email: tools@Karl-Voit.at
Requires-Python: >=3.9
Classifier: Development Status :: 5 - Production/Stable
Classifier: Environment :: Console
Classifier: Intended Audience :: End Users/Desktop
Classifier: License :: OSI Approved :: GNU General Public License v3 (GPLv3)
Classifier: License :: OSI Approved :: GNU General Public License v3 or later (GPLv3+)
Classifier: Operating System :: OS Independent
Classifier: Programming Language :: Python :: 3
Classifier: Programming Language :: Python :: 3.9
Classifier: Programming Language :: Python :: 3.10
Classifier: Programming Language :: Python :: 3.11
Classifier: Programming Language :: Python :: 3 :: Only
Requires-Dist: pyreadline3
